pitop/camera/__init__.py
pitop/camera/camera.py
pitop/camera/camera_calibration/__init__.py
pitop/camera/camera_calibration/camera_cal_dist_pickle_640-480.p
pitop/camera/camera_calibration/load_parameters.py
pitop/camera/core/__init__.py
pitop/camera/core/frame_handler.py
pitop/camera/core/cameras/__init__.py
pitop/camera/core/cameras/camera_types.py
pitop/camera/core/cameras/file_system_camera.py
pitop/camera/core/cameras/usb_camera.py
pitop/camera/core/capture_actions/__init__.py
pitop/camera/core/capture_actions/capture_action_base.py
pitop/camera/core/capture_actions/capture_actions.py
pitop/camera/core/capture_actions/generic_action.py
pitop/camera/core/capture_actions/motion_detector.py
pitop/camera/core/capture_actions/store_frame.py
pitop/camera/core/capture_actions/video_capture.py
pitop.camera-0.34.3.post1.dist-info/METADATA
pitop.camera-0.34.3.post1.dist-info/WHEEL
pitop.camera-0.34.3.post1.dist-info/top_level.txt
pitop.camera-0.34.3.post1.dist-info/RECORD
