Metadata-Version: 2.1
Name: pitop.camera
Version: 0.34.3.post1
Summary: Pi-top Python SDK.
Home-page: https://github.com/pi-top/pi-top-Python-SDK
Author: pi-top
Author-email: deb-maintainers@pi-top.com
License: Apache Software License
Keywords: pi-top,raspberrypi,battery
Platform: ALL
Classifier: Development Status :: 5 - Production/Stable
Classifier: Intended Audience :: Education
Classifier: Intended Audience :: Developers
Classifier: Topic :: Education
Classifier: Topic :: System :: Hardware
Classifier: License :: OSI Approved :: Apache Software License
Classifier: Programming Language :: Python :: 3
Classifier: Programming Language :: Python :: 3.7
Classifier: Programming Language :: Python :: 3.8
Classifier: Programming Language :: Python :: Implementation :: PyPy
Requires-Dist: pitop.common ==0.34.3-1
Requires-Dist: pitop.core ==0.34.3-1
Requires-Dist: pitop.pma ==0.34.3-1
Requires-Dist: pitop.processing ==0.34.3-1
Requires-Dist: imageio <3.0.0,>=2.4.1
Requires-Dist: numpy <2.0.0,>1.19.5
Requires-Dist: Pillow <9.0.0,>=8.1.2
Requires-Dist: opencv-python <5.0.0,>=4.5.0
